unitee/__init__.py
unitee/base_units.csv
unitee/consts.csv
unitee/derived_units.csv
unitee/prefixes.csv
unitee/unitee.py
unitee-0.1.6.dist-info/METADATA
unitee-0.1.6.dist-info/WHEEL
unitee-0.1.6.dist-info/RECORD
