Metadata-Version: 2.1
Name: unitee
Version: 0.1.6
Summary: super simple units
License: MIT
Author: 0Hughman0
Author-email: rammers2@hotmail.co.uk
Requires-Python: >=3.7,<4.0
Classifier: License :: OSI Approved :: MIT License
Classifier: Programming Language :: Python :: 3
Classifier: Programming Language :: Python :: 3.7
Classifier: Programming Language :: Python :: 3.8
Classifier: Programming Language :: Python :: 3.9
Classifier: Programming Language :: Python :: 3.10
Classifier: Programming Language :: Python :: 3.11
